scripts/cli.py
mqtt_leds_cli-1.0.0rc2.dist-info/METADATA
mqtt_leds_cli-1.0.0rc2.dist-info/WHEEL
mqtt_leds_cli-1.0.0rc2.dist-info/entry_points.txt
mqtt_leds_cli-1.0.0rc2.dist-info/RECORD
