Metadata-Version: 2.3
Name: mqtt-leds-cli
Version: 1.0.0rc2
Summary: This package makes it possible to control many types of led strips with the command line, using the mqtt-leds-lib library
License: Apache-2.0
Author: Guillaume Richard
Author-email: lord0gnome@gmail.com
Requires-Python: >=3.11,<4.0
Classifier: License :: OSI Approved :: Apache Software License
Classifier: Programming Language :: Python :: 3
Classifier: Programming Language :: Python :: 3.11
Classifier: Programming Language :: Python :: 3.12
Classifier: Programming Language :: Python :: 3.13
Requires-Dist: mqtt-leds-lib (==1.0.0rc2)
